GA22038UNO/__init__.py
GA22038UNO/linear_systems.py
GA22038UNO/nonlinear_systems.py
ga22038uno-0.1.0.dist-info/licenses/LICENSE
tests/__init__.py
tests/test_linear.py
tests/test_nonlinear.py
ga22038uno-0.1.0.dist-info/METADATA
ga22038uno-0.1.0.dist-info/WHEEL
ga22038uno-0.1.0.dist-info/top_level.txt
ga22038uno-0.1.0.dist-info/RECORD
