Metadata-Version: 2.4
Name: GA22038UNO
Version: 0.1.0
Summary: Librería para resolver sistemas de ecuaciones lineales y no lineales
Author: Tu Nombre
Author-email: tu_email@example.com
Classifier: Programming Language :: Python :: 3
Classifier: License :: OSI Approved :: MIT License
Requires-Python: >=3.7
License-File: LICENSE
Requires-Dist: numpy
Requires-Dist: matplotlib
Dynamic: author
Dynamic: author-email
Dynamic: classifier
Dynamic: license-file
Dynamic: requires-dist
Dynamic: requires-python
Dynamic: summary
